[
  {
    "name": "Albert Patterson",
    "description": "Software Engineer email: apatterson189@gmail.com and personal site www.ap.com",
    "email": "apatterson189@gmail.com",
    "linkedin": "https://www.linkedin.com/in/apattersoncmu/"
  },
  {
    "name": "bert",
    "description": "bbb",
    "email": "",
    "linkedin": ""
  },
  {
    "name": "kelly",
    "description": "jjj",
    "email": "",
    "linkedin": ""
  },
  {
    "name": "Harshneel",
    "description": "HH hh",
    "email": "",
    "linkedin": ""
  },
  {
    "name": "h2",
    "description": "hyasdf",
    "email": "",
    "linkedin": ""
  }
]